LICENSE
MANIFEST.in
README.md
setup.py
vs_tabletop_lite.egg-info/PKG-INFO
vs_tabletop_lite.egg-info/SOURCES.txt
vs_tabletop_lite.egg-info/dependency_links.txt
vs_tabletop_lite.egg-info/entry_points.txt
vs_tabletop_lite.egg-info/requires.txt
vs_tabletop_lite.egg-info/top_level.txt
vstabletop/__init__.py
vstabletop/config.py
vstabletop/forms.py
vstabletop/info.py
vstabletop/models.py
vstabletop/myDB.db
vstabletop/paths.py
vstabletop/questions.py
vstabletop/utils.py
vstabletop/games/__init__.py
vstabletop/games/routes_game1.py
vstabletop/games/routes_game2.py
vstabletop/games/routes_game3.py
vstabletop/games/routes_game4.py
vstabletop/games/routes_game5.py
vstabletop/games/routes_game6.py
vstabletop/games/routes_game7.py
vstabletop/games/routes_game8.py
vstabletop/main/__init__.py
vstabletop/main/app.py
vstabletop/main/events_calibration.py
vstabletop/main/routes_main.py
vstabletop/main/routes_scan.py
vstabletop/static/calibration.js
vstabletop/static/confetti.js
vstabletop/static/eyeplot.js
vstabletop/static/fabric.js
vstabletop/static/game.js
vstabletop/static/game1.js
vstabletop/static/game2.js
vstabletop/static/game3.js
vstabletop/static/game4.js
vstabletop/static/game5.js
vstabletop/static/game6.js
vstabletop/static/game7.js
vstabletop/static/game8.js
vstabletop/static/index.js
vstabletop/static/placeholder.png
vstabletop/static/scan.js
vstabletop/static/script.js
vstabletop/static/slicer.js
vstabletop/static/data/bw.mat
vstabletop/static/data/game4_phantom.mat
vstabletop/static/data/scan/user_uploaded.seq
vstabletop/static/data/solids/center_ball.npy
vstabletop/static/data/solids/center_ball.stl
vstabletop/static/data/solids/double_cone.npy
vstabletop/static/data/solids/double_cone.stl
vstabletop/static/data/solids/double_cone_rev.npy
vstabletop/static/data/solids/double_cone_rev.stl
vstabletop/static/data/solids/g7_set1_typeA.npy
vstabletop/static/data/solids/g7_set1_typeA.stl
vstabletop/static/data/solids/g7_set1_typeB.npy
vstabletop/static/data/solids/g7_set1_typeB.stl
vstabletop/static/data/solids/g7_set1_typeC.npy
vstabletop/static/data/solids/g7_set1_typeC.stl
vstabletop/static/data/solids/g7_set2_u135_d1.npy
vstabletop/static/data/solids/g7_set2_u135_d1.stl
