Metadata-Version: 2.1
Name: vs-tabletop-lite
Version: 1.0.0
Summary: Virtual Scanner Tabletop Games
Home-page: https://github.com/imr-framework/vs-tabletop
Author: imr-framework
Author-email: imr.framework2018@gmail.com
License: License :: OSI Approved :: GNU Affero General Public License v3
Platform: UNKNOWN
Classifier: Programming Language :: Python :: 3
Classifier: Programming Language :: Python :: 3.9
Requires-Python: >=3
License-File: LICENSE
